{
  "id": "ch06-mensuration",
  "subjectId": "maths-0580",
  "number": 6,
  "title": "Mensuration",
  "badge": "CH.6 MENSURATION",
  "summary": "Percentages, Financial Maths, Rates, and Time · Area & Circles · Sector & Segment Analysis · Volume & Surface Area · Similarity (Length, Are",
  "topicIds": [
    "3-1-percentages-financial-maths-rates-and-time",
    "5-1-5-2-area-circles",
    "5-3-5-4-sector-segment-analysis",
    "5-5-5-6-volume-surface-area",
    "5-7-similarity-length-area-volume-ratios"
  ],
  "accentColor": "teal",
  "hasChapterQuiz": true
}
