{
  "id": "6-5-finding-relationships-from-data-easy",
  "topicId": "6-5-finding-relationships-from-data",
  "chapterId": "ch06-coordinate-geometry",
  "difficulty": "easy",
  "title": "Finding Relationships from Data — Easy",
  "passPercent": 70,
  "questionsPerAttempt": 5,
  "pending": false,
  "questions": [
    {
      "id": "6-5-finding-relationships-from-data-easy-q1",
      "type": "mcq",
      "question": "Data $(x, y)$ satisfies $y = ax^2 + bx$. Which variables should be plotted on the $Y$ and $X$ axes?",
      "options": [
        "$Y = \\frac{y}{x}$ and $X = x$",
        "$Y = y$ and $X = x^2$",
        "$Y = \\lg y$ and $X = \\lg x$",
        "$Y = y$ and $X = x$"
      ],
      "correctIndex": 0,
      "explanation": "Dividing by $x$ gives $\\frac{y}{x} = ax + b$, so plot $Y = \\frac{y}{x}$ against $X = x$.\n\n**Common mistake:** Assuming every non-linear relationship requires logarithms."
    },
    {
      "id": "6-5-finding-relationships-from-data-easy-q2",
      "type": "mcq",
      "question": "For $y = Ab^x$, a plot of $\\lg y$ against $x$ has intercept $0.602$. Find $A$.",
      "options": [
        "4",
        "0.602",
        "10",
        "1.82"
      ],
      "correctIndex": 0,
      "explanation": "Intercept $c = \\lg A = 0.602$, so $A = 10^{0.602} \\approx 4$.\n\n**Common mistake:** Using base $e$ instead of base $10$ for $\\lg$."
    },
    {
      "id": "6-5-finding-relationships-from-data-easy-q3",
      "type": "mcq",
      "question": "Variables $p$ and $q$ satisfy $q = kp^n$. If $\\lg q$ is plotted against $\\lg p$, what does the gradient represent?",
      "options": [
        "$n$",
        "$\\lg k$",
        "$k$",
        "$\\lg n$"
      ],
      "correctIndex": 0,
      "explanation": "Log form: $\\lg q = n \\lg p + \\lg k$, so the gradient is $n$.\n\n**Common mistake:** Confusing the gradient with the intercept $\\lg k$."
    },
    {
      "id": "6-5-finding-relationships-from-data-easy-q4",
      "type": "mcq",
      "question": "Plotting $y$ against $\\frac{1}{x^2}$ gives a straight line through $(0, 5)$. For $y = \\frac{a}{x^2} + b$, find $b$.",
      "options": [
        "5",
        "0",
        "$a$",
        "$\\sqrt{5}$"
      ],
      "correctIndex": 0,
      "explanation": "The intercept when $X = 0$ gives $b = 5$.\n\n**Common mistake:** Assuming the line must pass through the origin."
    },
    {
      "id": "6-5-finding-relationships-from-data-easy-q5",
      "type": "mcq",
      "question": "A straight-line graph of $\\ln y$ against $x$ has gradient $-0.5$. Which equation links $x$ and $y$?",
      "options": [
        "$y = Ae^{-0.5x}$",
        "$y = Ax^{-0.5}$",
        "$y = -0.5e^x$",
        "$y = e^{-0.5}x$"
      ],
      "correctIndex": 0,
      "explanation": "$\\ln y = -0.5x + c$ gives $y = Ae^{-0.5x}$.\n\n**Common mistake:** Confusing this exponential law with a power law."
    }
  ]
}
