{
  "indexes": [
    {
      "collectionGroup": "profiles",
      "queryScope": "COLLECTION",
      "fields": [
        { "fieldPath": "schoolId", "order": "ASCENDING" },
        { "fieldPath": "xp", "order": "DESCENDING" }
      ]
    },
    {
      "collectionGroup": "profiles",
      "queryScope": "COLLECTION",
      "fields": [
        { "fieldPath": "clanIds", "arrayConfig": "CONTAINS" },
        { "fieldPath": "xp", "order": "DESCENDING" }
      ]
    },
    {
      "collectionGroup": "schools",
      "queryScope": "COLLECTION",
      "fields": [
        { "fieldPath": "type", "order": "ASCENDING" },
        { "fieldPath": "name", "order": "ASCENDING" }
      ]
    },
    {
      "collectionGroup": "schools",
      "queryScope": "COLLECTION",
      "fields": [
        { "fieldPath": "type", "order": "ASCENDING" },
        { "fieldPath": "nameNormalized", "order": "ASCENDING" }
      ]
    },
    {
      "collectionGroup": "friendRequests",
      "queryScope": "COLLECTION",
      "fields": [
        { "fieldPath": "toUid", "order": "ASCENDING" },
        { "fieldPath": "status", "order": "ASCENDING" }
      ]
    },
    {
      "collectionGroup": "friendRequests",
      "queryScope": "COLLECTION",
      "fields": [
        { "fieldPath": "fromUid", "order": "ASCENDING" },
        { "fieldPath": "status", "order": "ASCENDING" }
      ]
    }
  ],
  "fieldOverrides": []
}
